microbrewery/__init__.py
microbrewery/__main__.py
microbrewery/distiller.py
microbrewery-0.1.0rc1.dist-info/METADATA
microbrewery-0.1.0rc1.dist-info/WHEEL
microbrewery-0.1.0rc1.dist-info/entry_points.txt
microbrewery-0.1.0rc1.dist-info/licenses/LICENSE.md
microbrewery-0.1.0rc1.dist-info/RECORD
