Metadata-Version: 2.4
Name: microbrewery
Version: 0.1.0rc1
Summary: Tool for knowledge distillation into conversational LLMs
Project-URL: Documentation, https://github.com/ptaqqqq/microbrewery#readme
Project-URL: Issues, https://github.com/ptaqqqq/microbrewery/issues
Project-URL: Source, https://github.com/ptaqqqq/microbrewery
Author-email: Jakub Ptaszkiewicz <me@jakubptaszkiewicz.com>
License-Expression: MIT
License-File: LICENSE.md
Classifier: Development Status :: 3 - Alpha
Classifier: Operating System :: OS Independent
Classifier: Programming Language :: Python
Classifier: Programming Language :: Python :: 3.9
Classifier: Programming Language :: Python :: 3.10
Classifier: Programming Language :: Python :: 3.11
Classifier: Programming Language :: Python :: 3.12
Requires-Python: >=3.9
Requires-Dist: datasets>=4.0.0
Requires-Dist: huggingface-hub>=0.34.3
Requires-Dist: peft>=0.17.0
Requires-Dist: safetensors>=0.5.3
Requires-Dist: tokenizers>=0.21.4
Requires-Dist: torch
Requires-Dist: tqdm>=4.67.1
Requires-Dist: transformers>=4.54.1
Requires-Dist: trl>=0.20.0
